fair_random
