Metadata-Version: 2.1
Name: fair-random
Version: 0.0.5
Summary: fair random with hash prove
Home-page: https://github.com/et-repositories/fair-random
Author: et-repositories
Author-email: et-repositories@proton.me
License: UNKNOWN
Platform: UNKNOWN
License-File: LICENSE
